numparser/__init__.py
numparser/fsm/__init__.py
numparser/fsm/engine.py
numparser/fsm/parser.py
numparser/fsm/patterns.py
numparser/fsm/tokenizer.py
numparser/output.py
numparser2-1.0.2.dist-info/LICENSE
numparser2-1.0.2.dist-info/METADATA
numparser2-1.0.2.dist-info/WHEEL
numparser2-1.0.2.dist-info/RECORD
